[{
    "source": "nameList",
    "filter": "1<=paperRank<=4",
    "order": "paperRank",
    "profile": ["paperPts", "1", "2", "3", "4"],
    "property": {
      "rollingRank": [0, 0, 0, 0]
    }
  },
  {
    "source": "V02_1_unevenRolling",
    "filter": "1<=rank<=12",
    "order": "rank",
    "profile": ["paperPts", "1", "2", "3", "4"],
    "property": {
      "rollingRank": [1, 2, 3, 4, 5, 6, 7, 8, 9, 10, 11, 12]
    }
  },
  {
    "source": "V02_2_unevenRolling",
    "filter": "1<=rank<=12",
    "order": "rank",
    "profile": ["paperPts", "1", "2", "3", "4"],
    "property": {
      "rollingRank": [1, 2, 3, 4, 5, 6, 7, 8, 9, 10, 11, 12]
    }
  },
  {
    "source": "V02_3_unevenRolling",
    "filter": "1<=rank<=12",
    "order": "rank",
    "profile": ["paperPts", "1", "2", "3", "4"],
    "property": {
      "rollingRank": [1, 2, 3, 4, 5, 6, 7, 8, 9, 10, 11, 12]
    }
  }
]